setup.py
uvitools/__init__.py
uvitools/adapters.py
uvitools/broadcast.py
uvitools/debug.py
uvitools/routing.py
uvitools/utils.py
uvitools.egg-info/PKG-INFO
uvitools.egg-info/SOURCES.txt
uvitools.egg-info/dependency_links.txt
uvitools.egg-info/requires.txt
uvitools.egg-info/top_level.txt